py_app_dev/__init__.py
py_app_dev/core/__init__.py
py_app_dev/core/cmd_line.py
py_app_dev/core/compile_commands.py
py_app_dev/core/config.py
py_app_dev/core/data_registry.py
py_app_dev/core/docs_utils.py
py_app_dev/core/env_setup_scripts.py
py_app_dev/core/exceptions.py
py_app_dev/core/find.py
py_app_dev/core/logging.py
py_app_dev/core/pipeline.py
py_app_dev/core/runnable.py
py_app_dev/core/scoop_wrapper.py
py_app_dev/core/subprocess.py
py_app_dev/mvp/__init__.py
py_app_dev/mvp/event_manager.py
py_app_dev/mvp/presenter.py
py_app_dev/mvp/view.py
py_app_dev/py.typed
py_app_dev-2.18.0.dist-info/METADATA
py_app_dev-2.18.0.dist-info/WHEEL
py_app_dev-2.18.0.dist-info/licenses/LICENSE
py_app_dev-2.18.0.dist-info/RECORD
