Metadata-Version: 2.4
Name: py-app-dev
Version: 2.18.0
Summary: My application development modules.
License: MIT
License-File: LICENSE
Author: cuinixam
Author-email: cuinixam@me.com
Requires-Python: <4.0,>=3.10
Classifier: Development Status :: 2 - Pre-Alpha
Classifier: Intended Audience :: Developers
Classifier: Natural Language :: English
Classifier: Operating System :: OS Independent
Classifier: Topic :: Software Development :: Libraries
Requires-Dist: loguru (>=0.7,<1.0)
Requires-Dist: mashumaro (>=3.5,<4.0)
Project-URL: Bug Tracker, https://github.com/cuinixam/py-app-dev/issues
Project-URL: Changelog, https://github.com/cuinixam/py-app-dev/blob/main/CHANGELOG.md
Project-URL: Repository, https://github.com/cuinixam/py-app-dev
